src/sequential/decoder.sv
//==============================================================================
// File Name: decoder.sv
// Author: Francesco Mignone - ilnerdchuck
// Description: SECDED Decoder (Sequential) implementation
// Created: 2025-11-9
//==============================================================================

`timescale 1ps/1ps

import SECDED_ECC_pkg::*;

module SECDED_Decoder_seq(
    input logic clk,
    input logic rst_n,
    input logic [71:0] data_in,
    output logic [71:0] data_out,
    output logic error_detected,
    output logic single_error,
    output logic double_error
);

// Internal signals
logic [71:0] BUFFER_DATA;
logic [7:0] SYNDROME;
logic [7:0] received_parity;
logic [7:0] calculated_parity;

// Parity & syndrome section
assign received_parity = data_in[71:64];
assign calculated_parity = mega_xor(data_in[63:0]);

// Error detection and correction
assign data_out = ECC_correction(BUFFER_DATA, SYNDROME);
assign error_detected = |SYNDROME;
assign single_error = ^SYNDROME & error_detected;
assign double_error = ~^SYNDROME & error_detected;

always @(posedge clk or negedge rst_n) begin
    if (!rst_n) begin
        BUFFER_DATA <= '0;
        SYNDROME <= '0;
    end else begin
        BUFFER_DATA <= data_in;
        SYNDROME <= received_parity ^ calculated_parity;
    end
end


endmodule

src/noise.sv
`timescale 1ps/1ps

module noise(
    input logic [71:0] data_in,
    output logic [71:0] data_out
);
// Simple noise model: flip a single bit for demonstration
assign data_out = data_in ^ 72'b000000000000010000000000000;

endmodule

src/sequential/encoder.sv
//==============================================================================
// File Name: encoder.sv
// Author: Francesco Mignone - ilnerdchuck
// Description: SECDED Encoder (Sequential) implementation
// Created: 2025-11-9
//==============================================================================

`timescale 1ps/1ps
import SECDED_ECC_pkg::*;

module SECDED_Encoder_seq(
    input logic clk,
    input logic rst_n,
    input logic [63:0] data_in,
    output logic [71:0] data_out
);

/*
       |---|
       | b |
-data->| u |
       | f |
-clk-->| f |--------> data_out
       | e |
       | r |
       |---|
       | e |
 mega_xor-> | r |
       |---|

*/

// Internal signals
logic [71:0] BUFFER;

// Output assignments
assign data_out = BUFFER;

// Sequential logic to compute parity bits and store data into buffer
always @(posedge clk or negedge rst_n) begin
    if(!rst_n) 
        BUFFER <= 0;
    else begin
        BUFFER[63:0] <= data_in;
        // Calculate parity bits
        BUFFER[71:64] <= mega_xor(data_in);
    end
end

endmodule

src/testbenches/tb_seq.sv
// `include "encoder.sv"
// `include "decoder.sv"
// `include "./noise.sv"
`timescale 1ps/1ps

module tb_SECDED_ECC_seq;
logic clk;
logic rst_n;
logic error_detected;
logic single_error;
logic double_error;

logic [63:0] enc_data_in;
logic [71:0] enc_data_out;
logic [71:0] noisy_data_out;
logic [71:0] dec_data_out;

// Instantiate Encoder
SECDED_Encoder_seq enc_DUT_seq(
    .clk(clk),
    .rst_n(rst_n),
    .data_in(enc_data_in),
    .data_out(enc_data_out)
);

noise noise_DUT(
    .data_in(enc_data_out),
    .data_out(noisy_data_out)
);

// Instantiate Decoder
SECDED_Decoder_seq dec_DUT_seq(
    .clk(clk),
    .rst_n(rst_n),
    .data_in(noisy_data_out),
    .data_out(dec_data_out),
    .error_detected(error_detected),
    .single_error(single_error),
    .double_error(double_error)
);

localparam CLK_PERIOD = 10;
initial begin
    clk = 1'b0;
    forever #(CLK_PERIOD/2) clk = ~clk;
end
initial begin
    $dumpfile("build/tb_SECDED_seq.vcd");
    $dumpvars(0, tb_SECDED_ECC_seq);
end

initial begin

    $monitor("TIME: %0t | ENC_IN: 0x%h | ENC_OUT: 0x%h | DEC_OUT: 0x%h | ERR_DET: %b | S_ERR: %b | D_ERR: %b", 
              $time, enc_data_in, enc_data_out, dec_data_out, error_detected, single_error, double_error);

    $display("Time %0t - LOG: Starting SECDED ECC Sequential Testbench",$time);
    $display("Time %0t - LOG: Apply Reset",$time);
    rst_n = 1;
    enc_data_in = 0;
    #(CLK_PERIOD/2) rst_n = 0;
    repeat(2) @(posedge| clk);
    rst_n = 1;
    $display("Time %0t - LOG: Release Reset",$time);
    repeat(2) @(posedge clk);
    @(negedge clk);
    $display("---------------------------------------------------");
    $display("Time %0t - LOG: Start Applying Test Vectors",$time);
    $display("---------------------------------------------------");
    $display("Time %0t - LOG: Applying Test Vector 1: 0xDEADBEEF_CAFECAFE",$time);
    enc_data_in = 64'hDEADBEEF_CAFECAFE;
    repeat(2) @(negedge clk);
    no_error_1: assert (dec_data_out[63:0] == enc_data_in) else $error("Assertion no_error failed!");
    $display("Time %0t - LOG: Test Vector 1 Passed",$time);
    $display("---------------------------------------------------");
    $display("Time %0t - LOG: Applying Test Vector 2: 0x12345678_9ABCDEF0",$time);
    enc_data_in = 64'h12345678_9ABCDEF0;
    repeat(2) @(negedge clk);
    no_error_2: assert (dec_data_out[63:0] == enc_data_in) else $error("Assertion no_error failed!");
    $display("Time %0t - LOG: Test Vector 2 Passed",$time);
    $display("---------------------------------------------------");
    $display("Time %0t - LOG: All Test Vectors Passed",$time);  
    $finish(2);
end

endmodule
`default_nettype wire

build/tb_SECDED_seq.vcd
$date
	Mon Nov 10 00:04:22 2025
$end
$version
	Icarus Verilog
$end
$timescale
	1ps
$end
$scope module tb_SECDED_ECC_seq $end
$var wire 1 ! single_error $end
$var wire 72 " noisy_data_out [71:0] $end
$var wire 1 # error_detected $end
$var wire 72 $ enc_data_out [71:0] $end
$var wire 1 % double_error $end
$var wire 72 & dec_data_out [71:0] $end
$var parameter 32 ' CLK_PERIOD $end
$var reg 1 ( clk $end
$var reg 64 ) enc_data_in [63:0] $end
$var reg 1 * rst_n $end
$scope module dec_DUT_seq $end
$var wire 1 ( clk $end
$var wire 1 % double_error $end
$var wire 1 * rst_n $end
$var wire 1 ! single_error $end
$var wire 8 + received_parity [7:0] $end
$var wire 1 # error_detected $end
$var wire 72 , data_out [71:0] $end
$var wire 72 - data_in [71:0] $end
$var wire 8 . calculated_parity [7:0] $end
$var reg 72 / BUFFER_DATA [71:0] $end
$var reg 8 0 SYNDROME [7:0] $end
$upscope $end
$scope module enc_DUT_seq $end
$var wire 1 ( clk $end
$var wire 64 1 data_in [63:0] $end
$var wire 72 2 data_out [71:0] $end
$var wire 1 * rst_n $end
$var reg 72 3 BUFFER [71:0] $end
$upscope $end
$scope module noise_DUT $end
$var wire 72 4 data_in [71:0] $end
$var wire 72 5 data_out [71:0] $end
$upscope $end
$upscope $end
$enddefinitions $end
$comment Show the parameter values. $end
$dumpall
b1010 '
$end
#0
$dumpvars
bx 5
bx 4
bx 3
bx 2
b0 1
bx 0
bx /
bx .
bx -
bx ,
bx +
1*
b0 )
0(
bx &
x%
bx $
x#
bx "
x!
$end
#5
b100011 .
b0 +
b10000000000000 "
b10000000000000 -
b10000000000000 5
0!
0%
b0 &
b0 ,
b0 $
b0 2
b0 3
b0 4
0#
b0 0
b0 /
0*
1(
#10
0(
#15
1(
#20
0(
#25
1!
1#
b100011 0
b10000000000000 /
1*
1(
#30
0(
#35
1(
#40
0(
#45
1(
#50
b1101111010101101101111101110111111001010111111101100101011111110 )
b1101111010101101101111101110111111001010111111101100101011111110 1
0(
#55
b10110110 .
b10010101 +
b100101011101111010101101101111101110111111001010111111101110101011111110 "
b100101011101111010101101101111101110111111001010111111101110101011111110 -
b100101011101111010101101101111101110111111001010111111101110101011111110 5
b100101011101111010101101101111101110111111001010111111101100101011111110 $
b100101011101111010101101101111101110111111001010111111101100101011111110 2
b100101011101111010101101101111101110111111001010111111101100101011111110 3
b100101011101111010101101101111101110111111001010111111101100101011111110 4
1(
#60
0(
#65
b100101011101111010101101101111101110111111001010111111101100101011111110 &
b100101011101111010101101101111101110111111001010111111101100101011111110 ,
b100101011101111010101101101111101110111111001010111111101110101011111110 /
1(
#70
b1001000110100010101100111100010011010101111001101111011110000 )
b1001000110100010101100111100010011010101111001101111011110000 1
0(
#75
b1001001 .
b1101010 +
b11010100001001000110100010101100111100010011010101111001111111011110000 "
b11010100001001000110100010101100111100010011010101111001111111011110000 -
b11010100001001000110100010101100111100010011010101111001111111011110000 5
b11010100001001000110100010101100111100010011010101111001101111011110000 $
b11010100001001000110100010101100111100010011010101111001101111011110000 2
b11010100001001000110100010101100111100010011010101111001101111011110000 3
b11010100001001000110100010101100111100010011010101111001101111011110000 4
1(
#80
0(
#85
b11010100001001000110100010101100111100010011010101111001101111011110000 &
b11010100001001000110100010101100111100010011010101111001101111011110000 ,
b11010100001001000110100010101100111100010011010101111001111111011110000 /
1(
